{"Rows":{"Sizes":{"2":27.0,"4":27.0,"7":28.0,"9":27.0,"10":27.0,"11":27.0,"12":27.0,"21":27.0,"28":28.0},"Count":31},"Cols":{"InLogicalVisibleIndexes":[56,57,58,59,60,61,62,63,64,65],"Count":66},"Values":{"2,2":"借用编号：","2,15":"借用类型：","4,2":"借用日期：","4,15":"货品名称：","4,31":"借用人：","7,3":"货品编号","7,9":"货品名称","7,14":"规格","7,20":"数量","7,34":"剩余数量","7,41":"备注","8,14":"宽mm","8,17":"长m","8,20":"卷","8,23":"㎡","9,47":"删除","28,11":" ","28,21":"保存"},"Formulas":{"9,9":"IFERROR(ODATA(\"Storage_jcsj_货品信息表?$select=货品名称&$filter=ID eq \"&IF(ISBLANK(D10),\"null\",D10)),\"\")","9,23":"O10*R10*0.001*U10","9,34":"AA10-AE10"},"AttachInfos":{"2,6":{"CellType":{"$type":"Forguncy.TextCellType, ServerDesignerCommon","SavedValidators":[{"$type":"Forguncy.CellTypes.Models.UniqueValidadator, ServerDesignerCommon"}],"TemplateKey":"_RS_LightLine_Translucent_SmallRoundCorner_Normal1"},"BindingInfo":{"TableName":"备货表_子表","ColumnName":"借用编号"},"DataValidationInfo":{}},"2,19":{"CellType":{"$type":"Forguncy.DropDownListCellType, ServerDesignerCommon","ValidateItem":true,"TemplateKey":"_RS_LightLine_Translucent_SmallRoundCorner_Normal1","NoneItemText":"","Items":[{"Value":"订单","DisplayValue":"订单"},{"Value":"常规","DisplayValue":"常规"},{"Value":"样品","DisplayValue":"样品"}]},"BindingInfo":{"TableName":"备货表_子表","ColumnName":"借用类型"}},"4,6":{"CellType":{"$type":"Forguncy.DateCellType, ServerDesignerCommon","CellDefaultValue":{"$type":"Forguncy.Model.FormulaReferObject, ServerDesignerCommon","SerializeProperty":"=TODAY()"},"TemplateKey":"_RS_LightLine_Translucent_SmallRoundCorner_Normal1"},"BindingInfo":{"TableName":"备货表_子表","ColumnName":"借用日期"}},"4,19":{"CellType":{"$type":"Forguncy.DropDownListCellType, ServerDesignerCommon","TemplateKey":"_RS_LightLine_Translucent_SmallRoundCorner_Normal1","IsBounding":true,"Items":[{"Value":"项目1","DisplayValue":"项目1"},{"Value":"项目2","DisplayValue":"项目2"},{"Value":"项目3","DisplayValue":"项目3"}],"DataSource":"Storage_jcsj_货品信息表","ValueColumnBindingInfo":{"TableName":"Storage_jcsj_货品信息表","ColumnName":"货品名称"},"DisplayColumnBindingInfo":{"TableName":"Storage_jcsj_货品信息表","ColumnName":"货品名称"},"DropDownSubItems":[{"GUID":"62a758adb1b24d379c4586e35b2a8e12","ColumnName":"货品编号","BindingInfo":{"TableName":"Storage_jcsj_货品信息表","ColumnName":"货品编号"}},{"GUID":"9e1513da5c91456c8448c2b59e742f10","ColumnName":"货品名称","BindingInfo":{"TableName":"Storage_jcsj_货品信息表","ColumnName":"货品名称"}}]},"BindingInfo":{"TableName":"备货表_子表","ColumnName":"货品名称"}},"4,32":{"CellType":{"$type":"Forguncy.DropDownListCellType, ServerDesignerCommon","TemplateKey":"_RS_LightLine_Translucent_SmallRoundCorner_Normal1","IsBounding":true,"Items":[{"Value":"项目1","DisplayValue":"项目1"},{"Value":"项目2","DisplayValue":"项目2"},{"Value":"项目3","DisplayValue":"项目3"}],"DataSource":"行政管理_员工信息表","ValueColumnBindingInfo":{"TableName":"行政管理_员工信息表","ColumnName":"员工编号"},"DisplayColumnBindingInfo":{"TableName":"行政管理_员工信息表","ColumnName":"员工姓名"},"DropDownSubItems":[{"GUID":"63c71542166b410fa29770b140bb367b","ColumnName":"员工编号","BindingInfo":{"TableName":"行政管理_员工信息表","ColumnName":"员工编号"}},{"GUID":"65156b8f6df54e1ba8ae1490ed1877b4","ColumnName":"员工姓名","BindingInfo":{"TableName":"行政管理_员工信息表","ColumnName":"员工姓名"}}]},"BindingInfo":{"TableName":"备货表_子表","ColumnName":"借用人"}},"7,2":{"ListViewInfo":{"ShowColumnHeaderInDesigner":true,"TableName":"备货表_子表","RowIndex":7,"ColumnIndex":2,"ColumnCount":48,"RowCount":19,"ColumnHeaderRowCount":2,"IsRowHeaderVisible":true,"AllowEditInListview":true,"ShowGridLine":true,"Name":"表格1","DetailListViewInfo":{"MasterTable":"备货表","ColumnOfMasterTable":"ID","ColumnOfDetailTable":"备货单ID","DataCommitType":2},"SqlCondition":{"$type":"ForguncyDataAccess.GeneralCESqlCondition, ForguncyDataAccess","ColumnBindingInfo":{"TableName":"备货表_子表","ColumnName":"货品名称"},"Value":{"$type":"Forguncy.Model.FormulaReferObject, ServerDesignerCommon","SerializeProperty":"=借用单添加2!T5"},"Id":"f4ec5242-ef5b-493b-a313-71a8ddce7a9d"},"TopCondition":null,"CommitType":1,"ListViewStyleName":"全局设置"}},"9,3":{"BindingInfo":{"TableName":"备货表_子表","ColumnName":"货品主表ID","RelationBinding":{"RelatedTable":"Storage_jcsj_货品信息表","RelatedColumn":"ID","DisplayColumn":"货品编号"}}},"9,9":{"BindingInfo":{"TableName":"备货表_子表","ColumnName":"货品名称"}},"9,14":{"BindingInfo":{"TableName":"备货表_子表","ColumnName":"宽"}},"9,17":{"BindingInfo":{"TableName":"备货表_子表","ColumnName":"长"}},"9,20":{"BindingInfo":{"TableName":"备货表_子表","ColumnName":"卷"}},"9,23":{"BindingInfo":{"TableName":"备货表_子表","ColumnName":"平方米"}},"9,26":{"BindingInfo":{"TableName":"备货表_子表","ColumnName":"可借用数量"}},"9,30":{"CellType":{"$type":"Forguncy.TextCellType, ServerDesignerCommon","SavedValidators":[{"$type":"Forguncy.CellTypes.Models.UniqueValidadator, ServerDesignerCommon"}]},"BindingInfo":{"TableName":"备货表_子表","ColumnName":"借用数量"}},"9,34":{"BindingInfo":{"TableName":"备货表_子表","ColumnName":"剩余可借用数量"}},"9,38":{"BindingInfo":{"TableName":"备货表_子表","ColumnName":"备货人"}},"9,41":{"BindingInfo":{"TableName":"备货表_子表","ColumnName":"借货备注"}},"9,47":{"CellType":{"$type":"Forguncy.HyperlinkCellType, ServerDesignerCommon","CommandList":[{"$type":"Forguncy.Model.DeleteRecordCommand, ServerDesignerCommon","ShowConfirm":true,"ConfirmText":"您确定要删除吗？","UpdateValues":[]}],"Text":"删除","ClickMode":1}},"28,21":{"CellType":{"$type":"Forguncy.ButtonCellType, ServerDesignerCommon","CommandList":[{"$type":"Forguncy.Model.UpdateDataTableCommand, ServerDesignerCommon","TableName":"备货表_子表","ShowConfirm":false,"ConfirmText":"您确定要更新这行记录吗？","UpdateValues":[]},{"$type":"Forguncy.Model.NavigateCommand, ServerDesignerCommon","PageName":"借用单管理_","PassValues":[]}],"Text":"保存","TemplateKey":"_RS_Outline_Style2"}}},"StyleDatas":{"Styles":[{"FontFamily":0,"BorderBottom":null,"BorderTop":null,"BorderLeft":null,"BorderRight":null},{"FontFamily":0,"Formatter":1,"HorizontalAlignment":2,"BorderBottom":null,"BorderTop":null,"BorderLeft":null,"BorderRight":null},{"FontFamily":0,"Formatter":3,"BorderBottom":null,"BorderTop":null,"BorderLeft":null,"BorderRight":null},{"FontFamily":0,"Formatter":4,"BorderBottom":null,"BorderTop":null,"BorderLeft":null,"BorderRight":null},{"FontFamily":0,"HorizontalAlignment":2,"BorderBottom":null,"BorderTop":null,"BorderLeft":null,"BorderRight":null},{"BorderBottom":null,"BorderTop":null,"BorderLeft":null,"BorderRight":null},{"HorizontalAlignment":2,"BorderBottom":null,"BorderTop":null,"BorderLeft":null,"BorderRight":null},{"FontFamily":0,"BorderBottom":null,"BorderTop":0,"BorderLeft":0,"BorderRight":null},{"FontFamily":0,"FontSize":14.67,"BorderBottom":null,"BorderTop":0,"BorderLeft":null,"BorderRight":null},{"FontFamily":0,"BorderBottom":null,"BorderTop":0,"BorderLeft":null,"BorderRight":null},{"BorderBottom":null,"BorderTop":0,"BorderLeft":null,"BorderRight":null},{"FontFamily":0,"BorderBottom":null,"BorderTop":0,"BorderLeft":null,"BorderRight":0},{"FontFamily":0,"BorderBottom":null,"BorderTop":null,"BorderLeft":0,"BorderRight":null},{"FontFamily":0,"Formatter":6,"BorderBottom":null,"BorderTop":null,"BorderLeft":null,"BorderRight":null},{"FontFamily":0,"BorderBottom":null,"BorderTop":null,"BorderLeft":null,"BorderRight":0},{"FontFamily":0,"Formatter":7,"BorderBottom":null,"BorderTop":null,"BorderLeft":null,"BorderRight":null},{"Formatter":3,"BorderBottom":null,"BorderTop":null,"BorderLeft":null,"BorderRight":null},{"FontFamily":0,"Foreground":8,"HorizontalAlignment":9,"Underline":false,"BorderBottom":null,"BorderTop":null,"BorderLeft":null,"BorderRight":null},{"BorderBottom":null,"BorderTop":null,"BorderLeft":null,"BorderRight":0},{"BorderBottom":null,"BorderTop":null,"BorderLeft":0,"BorderRight":null},{"BorderBottom":0,"BorderTop":null,"BorderLeft":0,"BorderRight":null},{"BorderBottom":0,"BorderTop":null,"BorderLeft":null,"BorderRight":null},{"BorderBottom":0,"BorderTop":null,"BorderLeft":null,"BorderRight":0}],"Types":{"Strs":["Body","General","Right","@","yyyy/m/d","DarkGray","[AUTO]General","0.00","#FF00B0F0","Center"],"Borders":[{"Color":5}]},"CellStyles":{"1,55":0,"2,0":0,"2,2":1,"2,3":0,"2,4":0,"2,5":0,"2,6":2,"2,15":1,"2,16":0,"2,17":0,"2,18":0,"2,19":0,"2,55":0,"2,64":0,"3,2":0,"3,3":0,"3,4":0,"3,5":0,"3,6":0,"3,7":0,"3,8":0,"3,9":0,"3,10":0,"3,11":0,"3,12":0,"3,15":0,"3,16":0,"3,17":0,"3,18":0,"3,19":0,"3,20":0,"3,21":0,"3,22":0,"3,23":0,"3,24":0,"3,25":0,"3,26":0,"3,27":0,"3,28":0,"3,29":0,"3,30":0,"3,31":0,"3,32":0,"3,33":0,"3,52":0,"3,53":0,"3,54":0,"3,55":0,"4,0":0,"4,2":1,"4,3":0,"4,4":0,"4,5":0,"4,6":3,"4,15":4,"4,16":0,"4,17":0,"4,18":0,"4,19":0,"4,29":5,"4,30":5,"4,31":6,"4,39":5,"4,40":5,"4,55":0,"5,0":0,"5,55":0,"5,59":0,"5,60":0,"5,61":0,"5,62":0,"5,63":0,"5,64":0,"6,0":0,"6,55":0,"7,0":0,"7,2":7,"7,3":8,"7,4":9,"7,5":9,"7,6":9,"7,7":9,"7,8":9,"7,9":8,"7,10":9,"7,11":9,"7,12":9,"7,13":9,"7,14":9,"7,15":9,"7,16":9,"7,17":9,"7,18":9,"7,19":9,"7,20":9,"7,21":9,"7,22":9,"7,23":9,"7,24":9,"7,25":9,"7,26":8,"7,27":10,"7,28":10,"7,29":10,"7,30":10,"7,31":10,"7,32":10,"7,33":10,"7,34":10,"7,35":10,"7,36":10,"7,37":10,"7,38":10,"7,39":10,"7,40":10,"7,41":8,"7,42":10,"7,43":10,"7,44":10,"7,45":10,"7,46":10,"7,47":9,"7,48":9,"7,49":11,"7,55":0,"7,64":0,"8,2":12,"8,3":0,"8,4":0,"8,5":0,"8,6":0,"8,7":0,"8,8":0,"8,9":0,"8,10":0,"8,11":0,"8,12":0,"8,13":0,"8,14":13,"8,15":0,"8,16":0,"8,17":5,"8,18":5,"8,19":5,"8,20":13,"8,21":0,"8,22":0,"8,23":13,"8,24":0,"8,25":0,"8,26":5,"8,27":5,"8,28":5,"8,29":5,"8,30":5,"8,31":5,"8,32":5,"8,33":5,"8,34":5,"8,35":5,"8,36":5,"8,37":5,"8,47":0,"8,48":0,"8,49":14,"8,55":0,"9,2":12,"9,3":0,"9,9":0,"9,10":0,"9,11":0,"9,12":0,"9,13":0,"9,14":0,"9,15":5,"9,16":5,"9,17":5,"9,18":5,"9,19":5,"9,20":0,"9,21":5,"9,22":5,"9,23":15,"9,24":0,"9,25":0,"9,26":0,"9,27":5,"9,28":5,"9,29":5,"9,30":16,"9,31":5,"9,32":5,"9,33":5,"9,34":5,"9,35":5,"9,36":5,"9,37":5,"9,41":0,"9,47":17,"9,48":0,"9,49":14,"9,55":0,"10,2":12,"10,3":0,"10,4":0,"10,5":0,"10,6":0,"10,7":0,"10,8":0,"10,9":0,"10,10":0,"10,11":0,"10,12":0,"10,13":0,"10,14":0,"10,15":0,"10,16":0,"10,17":0,"10,18":0,"10,19":0,"10,20":0,"10,21":0,"10,22":0,"10,23":0,"10,24":0,"10,25":0,"10,26":0,"10,27":0,"10,28":0,"10,29":0,"10,30":0,"10,31":0,"10,32":0,"10,33":0,"10,34":0,"10,35":0,"10,36":0,"10,37":0,"10,38":0,"10,39":5,"10,40":5,"10,41":5,"10,42":5,"10,43":5,"10,44":5,"10,45":5,"10,46":5,"10,47":5,"10,48":5,"10,49":18,"10,55":0,"11,2":12,"11,3":0,"11,4":0,"11,5":0,"11,6":0,"11,7":0,"11,8":0,"11,9":0,"11,10":0,"11,11":0,"11,12":0,"11,13":0,"11,14":0,"11,15":0,"11,16":0,"11,17":0,"11,18":0,"11,19":0,"11,20":0,"11,21":0,"11,22":0,"11,23":0,"11,24":0,"11,25":0,"11,26":0,"11,27":0,"11,28":0,"11,29":0,"11,30":0,"11,31":0,"11,32":0,"11,33":0,"11,34":0,"11,35":0,"11,36":0,"11,37":0,"11,38":0,"11,39":5,"11,40":5,"11,41":5,"11,42":5,"11,43":5,"11,44":5,"11,45":5,"11,46":5,"11,47":5,"11,48":5,"11,49":18,"11,55":0,"12,2":12,"12,3":0,"12,4":0,"12,5":0,"12,6":0,"12,7":0,"12,8":0,"12,9":0,"12,10":0,"12,11":0,"12,12":0,"12,13":0,"12,14":0,"12,15":0,"12,16":0,"12,17":0,"12,18":0,"12,19":0,"12,20":0,"12,21":0,"12,22":0,"12,23":0,"12,24":0,"12,25":0,"12,26":0,"12,27":0,"12,28":0,"12,29":0,"12,30":0,"12,31":0,"12,32":0,"12,33":0,"12,34":0,"12,35":0,"12,36":0,"12,37":0,"12,38":0,"12,39":5,"12,40":5,"12,41":5,"12,42":5,"12,43":5,"12,44":5,"12,45":5,"12,46":5,"12,47":5,"12,48":5,"12,49":18,"12,55":0,"13,2":12,"13,3":0,"13,4":0,"13,5":0,"13,6":0,"13,7":0,"13,8":0,"13,9":0,"13,10":0,"13,11":0,"13,12":0,"13,13":0,"13,14":0,"13,15":0,"13,16":0,"13,17":0,"13,18":0,"13,19":0,"13,20":0,"13,21":0,"13,22":0,"13,23":0,"13,24":0,"13,25":0,"13,26":0,"13,27":0,"13,28":0,"13,29":0,"13,30":0,"13,31":0,"13,32":0,"13,33":0,"13,34":0,"13,35":0,"13,36":0,"13,37":0,"13,38":0,"13,39":5,"13,40":5,"13,41":5,"13,42":5,"13,43":5,"13,44":5,"13,45":5,"13,46":5,"13,47":5,"13,48":5,"13,49":18,"13,55":0,"14,2":12,"14,3":0,"14,4":0,"14,5":0,"14,6":0,"14,7":0,"14,8":0,"14,9":0,"14,10":0,"14,11":0,"14,12":0,"14,13":0,"14,14":0,"14,15":0,"14,16":0,"14,17":0,"14,18":0,"14,19":0,"14,20":0,"14,21":0,"14,22":0,"14,23":0,"14,24":0,"14,25":0,"14,26":0,"14,27":0,"14,28":0,"14,29":0,"14,30":0,"14,31":0,"14,32":0,"14,33":0,"14,34":0,"14,35":0,"14,36":0,"14,37":0,"14,38":0,"14,39":5,"14,40":5,"14,41":5,"14,42":5,"14,43":5,"14,44":5,"14,45":5,"14,46":5,"14,47":5,"14,48":5,"14,49":18,"14,55":0,"15,2":12,"15,3":0,"15,4":0,"15,5":0,"15,6":0,"15,7":0,"15,8":0,"15,9":0,"15,10":0,"15,11":0,"15,12":0,"15,13":0,"15,14":0,"15,15":0,"15,16":0,"15,17":0,"15,18":0,"15,19":0,"15,20":0,"15,21":0,"15,22":0,"15,23":0,"15,24":0,"15,25":0,"15,26":0,"15,27":0,"15,28":0,"15,29":0,"15,30":0,"15,31":0,"15,32":0,"15,33":0,"15,34":0,"15,35":0,"15,36":0,"15,37":0,"15,38":0,"15,39":5,"15,40":5,"15,41":5,"15,42":5,"15,43":5,"15,44":5,"15,45":5,"15,46":5,"15,47":5,"15,48":5,"15,49":18,"15,55":0,"16,2":12,"16,3":0,"16,4":0,"16,5":0,"16,6":0,"16,7":0,"16,8":0,"16,9":0,"16,10":0,"16,11":0,"16,12":0,"16,13":0,"16,14":0,"16,15":0,"16,16":0,"16,17":0,"16,18":0,"16,19":0,"16,20":0,"16,21":0,"16,22":0,"16,23":0,"16,24":0,"16,25":0,"16,26":0,"16,27":0,"16,28":0,"16,29":0,"16,30":0,"16,31":0,"16,32":0,"16,33":0,"16,34":0,"16,35":0,"16,36":0,"16,37":0,"16,38":0,"16,39":5,"16,40":5,"16,41":5,"16,42":5,"16,43":5,"16,44":5,"16,45":5,"16,46":5,"16,47":5,"16,48":5,"16,49":18,"16,55":0,"17,2":12,"17,3":0,"17,4":0,"17,5":0,"17,6":0,"17,7":0,"17,8":0,"17,9":0,"17,10":0,"17,11":0,"17,12":0,"17,13":0,"17,14":0,"17,15":0,"17,16":0,"17,17":0,"17,18":0,"17,19":0,"17,20":0,"17,21":0,"17,22":0,"17,23":0,"17,24":0,"17,25":0,"17,26":0,"17,27":0,"17,28":0,"17,29":0,"17,30":0,"17,31":0,"17,32":0,"17,33":0,"17,34":0,"17,35":0,"17,36":0,"17,37":0,"17,38":0,"17,39":5,"17,40":5,"17,41":5,"17,42":5,"17,43":5,"17,44":5,"17,45":5,"17,46":5,"17,47":5,"17,48":5,"17,49":18,"17,55":0,"18,2":12,"18,3":0,"18,4":0,"18,5":0,"18,6":0,"18,7":0,"18,8":0,"18,9":0,"18,10":0,"18,11":0,"18,12":0,"18,13":0,"18,14":0,"18,15":0,"18,16":0,"18,17":0,"18,18":0,"18,19":0,"18,20":0,"18,21":0,"18,22":0,"18,23":0,"18,24":0,"18,25":0,"18,26":0,"18,27":0,"18,28":0,"18,29":0,"18,30":0,"18,31":0,"18,32":0,"18,33":0,"18,34":0,"18,35":0,"18,36":0,"18,37":0,"18,38":0,"18,39":5,"18,40":5,"18,41":5,"18,42":5,"18,43":5,"18,44":5,"18,45":5,"18,46":5,"18,47":5,"18,48":5,"18,49":18,"18,55":0,"19,2":12,"19,3":0,"19,4":0,"19,5":0,"19,6":0,"19,7":0,"19,8":0,"19,9":0,"19,10":0,"19,11":0,"19,12":0,"19,13":0,"19,14":0,"19,15":0,"19,16":0,"19,17":0,"19,18":0,"19,19":0,"19,20":0,"19,21":0,"19,22":0,"19,23":0,"19,24":0,"19,25":0,"19,26":0,"19,27":0,"19,28":0,"19,29":0,"19,30":0,"19,31":0,"19,32":0,"19,33":0,"19,34":0,"19,35":0,"19,36":0,"19,37":0,"19,38":0,"19,39":5,"19,40":5,"19,41":5,"19,42":5,"19,43":5,"19,44":5,"19,45":5,"19,46":5,"19,47":5,"19,48":5,"19,49":18,"19,55":0,"20,2":12,"20,3":0,"20,4":0,"20,5":0,"20,6":0,"20,7":0,"20,8":0,"20,9":0,"20,10":0,"20,11":0,"20,12":0,"20,13":0,"20,14":0,"20,15":0,"20,16":0,"20,17":0,"20,18":0,"20,19":0,"20,20":0,"20,21":0,"20,22":0,"20,23":0,"20,24":0,"20,25":0,"20,26":0,"20,27":0,"20,28":0,"20,29":0,"20,30":0,"20,31":0,"20,32":0,"20,33":0,"20,34":0,"20,35":0,"20,36":0,"20,37":0,"20,38":0,"20,39":5,"20,40":5,"20,41":5,"20,42":5,"20,43":5,"20,44":5,"20,45":5,"20,46":5,"20,47":5,"20,48":5,"20,49":18,"20,55":0,"21,2":12,"21,3":0,"21,4":0,"21,5":0,"21,6":0,"21,7":0,"21,8":0,"21,9":0,"21,10":0,"21,11":0,"21,12":0,"21,13":0,"21,14":0,"21,15":0,"21,16":0,"21,17":0,"21,18":0,"21,19":0,"21,20":0,"21,21":0,"21,22":0,"21,23":0,"21,24":0,"21,25":0,"21,26":0,"21,27":0,"21,28":0,"21,29":0,"21,30":0,"21,31":0,"21,32":0,"21,33":0,"21,34":0,"21,35":0,"21,36":0,"21,37":0,"21,38":0,"21,39":5,"21,40":5,"21,41":5,"21,42":5,"21,43":5,"21,44":5,"21,45":5,"21,46":5,"21,47":5,"21,48":5,"21,49":18,"21,55":0,"22,2":12,"22,3":0,"22,4":0,"22,5":0,"22,6":0,"22,7":0,"22,8":0,"22,9":0,"22,10":0,"22,11":0,"22,12":0,"22,13":0,"22,14":0,"22,15":0,"22,16":0,"22,17":0,"22,18":0,"22,19":0,"22,20":0,"22,21":0,"22,22":0,"22,23":0,"22,24":0,"22,25":0,"22,26":0,"22,27":0,"22,28":0,"22,29":0,"22,30":0,"22,31":0,"22,32":0,"22,33":0,"22,34":0,"22,35":0,"22,36":0,"22,37":0,"22,38":0,"22,39":5,"22,40":5,"22,41":5,"22,42":5,"22,43":5,"22,44":5,"22,45":5,"22,46":5,"22,47":5,"22,48":5,"22,49":18,"22,55":0,"23,2":12,"23,3":0,"23,4":0,"23,5":0,"23,6":0,"23,7":0,"23,8":0,"23,9":0,"23,10":0,"23,11":0,"23,12":0,"23,13":0,"23,14":0,"23,15":0,"23,16":0,"23,17":0,"23,18":0,"23,19":0,"23,20":0,"23,21":0,"23,22":0,"23,23":0,"23,24":0,"23,25":0,"23,26":0,"23,27":0,"23,28":0,"23,29":0,"23,30":0,"23,31":0,"23,32":0,"23,33":0,"23,34":0,"23,35":0,"23,36":0,"23,37":0,"23,38":0,"23,39":5,"23,40":5,"23,41":5,"23,42":5,"23,43":5,"23,44":5,"23,45":5,"23,46":5,"23,47":5,"23,48":5,"23,49":18,"23,55":0,"24,2":19,"24,3":5,"24,4":5,"24,5":5,"24,6":5,"24,7":5,"24,8":5,"24,9":5,"24,10":5,"24,11":5,"24,12":5,"24,13":5,"24,14":5,"24,15":5,"24,16":5,"24,17":5,"24,18":5,"24,19":5,"24,20":5,"24,21":5,"24,22":5,"24,23":5,"24,24":5,"24,25":5,"24,26":5,"24,27":5,"24,28":5,"24,29":5,"24,30":5,"24,31":5,"24,32":5,"24,33":5,"24,34":5,"24,35":5,"24,36":5,"24,37":5,"24,38":5,"24,39":5,"24,40":5,"24,41":5,"24,42":5,"24,43":5,"24,44":5,"24,45":5,"24,46":5,"24,47":5,"24,48":5,"24,49":18,"24,55":0,"25,2":20,"25,3":21,"25,4":21,"25,5":21,"25,6":21,"25,7":21,"25,8":21,"25,9":21,"25,10":21,"25,11":21,"25,12":21,"25,13":21,"25,14":21,"25,15":21,"25,16":21,"25,17":21,"25,18":21,"25,19":21,"25,20":21,"25,21":21,"25,22":21,"25,23":21,"25,24":21,"25,25":21,"25,26":21,"25,27":21,"25,28":21,"25,29":21,"25,30":21,"25,31":21,"25,32":21,"25,33":21,"25,34":21,"25,35":21,"25,36":21,"25,37":21,"25,38":21,"25,39":21,"25,40":21,"25,41":21,"25,42":21,"25,43":21,"25,44":21,"25,45":21,"25,46":21,"25,47":21,"25,48":21,"25,49":22,"25,55":0,"26,55":0,"27,55":0,"28,21":13,"28,22":0,"28,23":0,"28,55":0,"29,55":0},"SheetStyle":{"FontFamily":0,"BorderBottom":null,"BorderTop":null,"BorderLeft":null,"BorderRight":null}},"Spans":["2,2,1,4","2,6,1,7","2,15,1,4","2,19,1,7","4,2,1,4","4,6,1,7","4,15,1,4","4,19,1,7","4,32,1,7","7,2,2,1","7,3,2,6","7,9,2,5","7,14,1,6","7,20,1,6","7,26,2,4","7,30,2,4","7,34,2,4","7,38,2,3","7,41,2,6","7,47,2,3","8,14,1,3","8,17,1,3","8,20,1,3","8,23,1,3","9,3,1,6","9,9,1,5","9,14,1,3","9,17,1,3","9,20,1,3","9,23,1,3","9,26,1,4","9,30,1,4","9,34,1,4","9,38,1,3","9,41,1,6","9,47,1,3","10,2,16,48","28,21,1,3","28,24,1,3"],"BackgroundPictures":[{"StyleInfo":{"Fill":"Background 1 -5"},"IsAutomaticFill":false,"Name":"cf0d2663-ada8-42d0-b2fa-b280b7f41762","Size":"1320,685"},{"StyleInfo":{"Fill":"Background 1 0"},"IsAutomaticFill":false,"Name":"ac136c0c-4cbf-4788-bf13-c5c3c1861e14","Location":"20,20","Size":"1282,645"},{"StyleInfo":{"Fill":"Background 1 -5"},"IsAutomaticFill":false,"Name":"49ab80a8-66f2-4d75-83bc-83879f812ade","Location":"1100,20","Size":"20,645"}],"PageInfo":{"$type":"Forguncy.Model.Pages.NormalPage, ServerDesignerCommon","MasterPageName":"01_销售管理母版页","PageLoadedCommandList":[{"$type":"Forguncy.Model.QueryCommand, ServerDesignerCommon","TargetTableName":"备货表_子表","SqlCondition":{"$type":"ForguncyDataAccess.GeneralCESqlCondition, ForguncyDataAccess","ColumnBindingInfo":{"TableName":"备货表_子表","ColumnName":"货品名称"},"Value":{"$type":"Forguncy.Model.FormulaReferObject, ServerDesignerCommon","SerializeProperty":"=借用单添加2!T5"},"Id":"bbbf91a8-da74-4792-9ff4-b401138ebe0d"},"Params":["=T5"],"ID":"d6775eceaa6548e0b16ab9fdeb50af36"}],"AuthorizeInfo":{"VisitMode":6,"AllowVisitedRoles":["Administrator","总经理","销售"]},"RowBreakLines":[],"RepeatRangeSettings":[]},"PrintInfo":{"Margin":{},"PaperSize":{}}}