{"Rows":{"Sizes":{"1":27.0,"2":10.0,"3":27.0,"4":27.0,"5":10.0,"6":27.0,"7":27.0,"8":27.0,"19":17.0,"20":15.0,"21":27.0},"Count":24},"Cols":{"InLogicalVisibleIndexes":[40],"Count":50},"Values":{"6,10":"货品名称","6,15":"货品规格","6,20":"货品型号","6,25":"计量单位","6,30":"货品属性","6,35":"获取方式","6,41":"备注","21,37":"确定","21,42":"取消"},"AttachInfos":{"1,4":{"CellType":{"$type":"Forguncy.TextCellType, ServerDesignerCommon","SavedValidators":[{"$type":"Forguncy.CellTypes.Models.UniqueValidadator, ServerDesignerCommon"}],"TemplateKey":"_RS_LightLine_Translucent_SmallRoundCorner_Normal1","WaterMark":"货品编号/货品名称/货品规格/货品型号"}},"3,4":{"CellType":{"$type":"SelectionPanel.SelectionPanel, SelectionPanel","ListViewName":"xBOM子件选择表","DisplayColumnIndex":2}},"6,4":{"ListViewInfo":{"ShowColumnHeaderInDesigner":true,"TableName":"Storage_jcsj_货品信息表","RowIndex":6,"ColumnIndex":4,"ColumnCount":42,"RowCount":14,"IsRowHeaderCheckBoxVisible":true,"SelectionMode":1,"ShowGridLine":true,"Name":"xBOM子件选择表","SqlCondition":{"$type":"ForguncyDataAccess.RelationSqlCondition, ForguncyDataAccess","Condition1":{"$type":"ForguncyDataAccess.RelationSqlCondition, ForguncyDataAccess","Condition1":{"$type":"ForguncyDataAccess.RelationSqlCondition, ForguncyDataAccess","Condition1":{"$type":"ForguncyDataAccess.TextCESqlCondition, ForguncyDataAccess","CompareType":6,"ColumnBindingInfo":{"TableName":"Storage_jcsj_货品信息表","ColumnName":"货品编号"},"Value":{"$type":"Forguncy.Model.FormulaReferObject, ServerDesignerCommon","SerializeProperty":"=盘点单货品选择!E2"},"Id":"472806fa-8089-4636-a2bd-2ccf58a39ede"},"Condition2":{"$type":"ForguncyDataAccess.TextCESqlCondition, ForguncyDataAccess","CompareType":6,"ColumnBindingInfo":{"TableName":"Storage_jcsj_货品信息表","ColumnName":"货品名称"},"Value":{"$type":"Forguncy.Model.FormulaReferObject, ServerDesignerCommon","SerializeProperty":"=盘点单货品选择!E2"},"Id":"2915bec4-7995-43f8-9b8b-a4af186bcf70"},"RelationType":1,"Id":"1cf374b7-a90f-4e66-b39e-9e9db48c7bda"},"Condition2":{"$type":"ForguncyDataAccess.TextCESqlCondition, ForguncyDataAccess","CompareType":6,"ColumnBindingInfo":{"TableName":"Storage_jcsj_货品信息表","ColumnName":"规格"},"Value":{"$type":"Forguncy.Model.FormulaReferObject, ServerDesignerCommon","SerializeProperty":"=盘点单货品选择!E2"},"Id":"3f71e632-33fa-40f0-b940-db3d667abc9b"},"RelationType":1,"Id":"7e822fd0-fbc1-42d4-91aa-69b80cd8265d"},"Condition2":{"$type":"ForguncyDataAccess.TextCESqlCondition, ForguncyDataAccess","CompareType":6,"ColumnBindingInfo":{"TableName":"Storage_jcsj_货品信息表","ColumnName":"型号"},"Value":{"$type":"Forguncy.Model.FormulaReferObject, ServerDesignerCommon","SerializeProperty":"=盘点单货品选择!E2"},"Id":"72eec70c-792e-4291-9844-dad25b8cab7d"},"RelationType":1,"Id":"ca98646f-b1d7-4278-b442-7ddae5cdf3ef"},"TopCondition":null,"ListViewStyleName":"_RS_None"}},"7,5":{"BindingInfo":{"TableName":"Storage_jcsj_货品信息表","ColumnName":"货品编号"}},"7,10":{"BindingInfo":{"TableName":"Storage_jcsj_货品信息表","ColumnName":"货品名称"}},"7,15":{"BindingInfo":{"TableName":"Storage_jcsj_货品信息表","ColumnName":"规格"}},"7,20":{"BindingInfo":{"TableName":"Storage_jcsj_货品信息表","ColumnName":"型号"}},"7,25":{"BindingInfo":{"TableName":"Storage_jcsj_货品信息表","ColumnName":"单位"}},"7,30":{"BindingInfo":{"TableName":"Storage_jcsj_货品信息表","ColumnName":"货品属性"}},"7,35":{"BindingInfo":{"TableName":"Storage_jcsj_货品信息表","ColumnName":"获取途径"}},"7,40":{"BindingInfo":{"TableName":"Storage_jcsj_货品信息表","ColumnName":"ID"}},"7,41":{"BindingInfo":{"TableName":"Storage_jcsj_货品信息表","ColumnName":"Remark"}},"21,37":{"CellType":{"$type":"Forguncy.ButtonCellType, ServerDesignerCommon","CommandList":[{"$type":"PassListviewDataCommand.PassListviewDataCommand, PassListviewDataCommand","PassRowMode":1,"PassValueItems":[{"SourceCell":{"$type":"Forguncy.Model.FormulaReferObject, ServerDesignerCommon","SerializeProperty":"=盘点单货品选择!AO8"},"TargetCell":"子件ID"}]},{"$type":"Forguncy.Model.ClosePopupCommand, ServerDesignerCommon"}],"Text":"确定","TemplateKey":"_RS_Normal_Style2"}},"21,42":{"CellType":{"$type":"Forguncy.ButtonCellType, ServerDesignerCommon","CommandList":[{"$type":"Forguncy.Model.ClosePopupCommand, ServerDesignerCommon"}],"Text":"取消","TemplateKey":"_RS_Outline_Style2"}}},"StyleDatas":{"Styles":[{"FontFamily":0},{"FontFamily":0,"BorderBottom":null,"BorderTop":0,"BorderLeft":0},{"FontFamily":0,"BorderBottom":null,"BorderTop":0},{"FontFamily":0,"Formatter":2,"BorderBottom":null,"BorderTop":0},{"FontFamily":0,"BorderBottom":null,"BorderTop":0,"BorderRight":0},{"FontFamily":0,"BorderBottom":null,"BorderTop":null,"BorderLeft":0},{"FontFamily":0,"BorderBottom":null,"BorderTop":null},{"FontFamily":0,"BorderBottom":null,"BorderTop":null,"BorderRight":0},{"BorderBottom":null,"BorderTop":null,"BorderLeft":0},{"BorderBottom":null,"BorderTop":null},{"BorderBottom":null,"BorderTop":null,"BorderRight":0},{"FontFamily":0,"BorderBottom":0,"BorderTop":null,"BorderLeft":0},{"FontFamily":0,"BorderBottom":0,"BorderTop":null},{"FontFamily":0,"BorderBottom":0,"BorderTop":null,"BorderRight":0}],"Types":{"Strs":["Body","DarkGray","[AUTO]General"],"Borders":[{"Color":1}]},"CellStyles":{"1,2":0,"1,4":0,"1,5":0,"1,6":0,"1,7":0,"1,8":0,"1,9":0,"1,10":0,"1,11":0,"1,12":0,"1,13":0,"1,14":0,"1,15":0,"1,16":0,"1,17":0,"1,18":0,"1,19":0,"1,20":0,"1,21":0,"1,22":0,"1,23":0,"1,24":0,"1,25":0,"1,26":0,"1,27":0,"1,28":0,"1,29":0,"1,30":0,"1,31":0,"1,32":0,"1,33":0,"1,34":0,"1,35":0,"1,36":0,"1,37":0,"1,38":0,"1,39":0,"1,40":0,"1,41":0,"1,42":0,"2,2":0,"2,3":0,"2,4":0,"2,5":0,"2,6":0,"2,7":0,"2,8":0,"2,9":0,"2,10":0,"2,11":0,"2,12":0,"2,13":0,"2,14":0,"2,15":0,"2,16":0,"2,17":0,"2,18":0,"2,19":0,"2,20":0,"2,21":0,"2,22":0,"2,23":0,"2,24":0,"2,25":0,"2,26":0,"2,27":0,"2,28":0,"2,29":0,"2,30":0,"2,31":0,"2,32":0,"2,33":0,"2,34":0,"2,35":0,"2,36":0,"2,37":0,"2,38":0,"2,39":0,"2,40":0,"2,41":0,"2,42":0,"3,4":0,"5,2":0,"5,3":0,"5,4":0,"5,5":0,"5,6":0,"5,7":0,"5,8":0,"5,9":0,"5,10":0,"5,11":0,"5,12":0,"5,13":0,"5,14":0,"5,15":0,"5,16":0,"5,17":0,"5,18":0,"5,19":0,"5,20":0,"5,21":0,"5,22":0,"5,23":0,"5,24":0,"5,25":0,"5,26":0,"5,27":0,"5,28":0,"5,29":0,"5,30":0,"5,31":0,"5,32":0,"5,33":0,"5,34":0,"5,35":0,"5,36":0,"5,37":0,"5,38":0,"5,39":0,"5,40":0,"5,41":0,"5,42":0,"6,4":1,"6,5":2,"6,6":2,"6,7":2,"6,8":2,"6,9":2,"6,10":2,"6,11":2,"6,12":2,"6,13":2,"6,14":2,"6,15":2,"6,16":2,"6,17":2,"6,18":2,"6,19":2,"6,20":2,"6,21":2,"6,22":2,"6,23":2,"6,24":2,"6,25":2,"6,26":2,"6,27":2,"6,28":2,"6,29":2,"6,30":2,"6,31":2,"6,32":2,"6,33":2,"6,34":2,"6,35":2,"6,36":2,"6,37":2,"6,38":2,"6,39":2,"6,40":2,"6,41":3,"6,42":2,"6,43":2,"6,44":2,"6,45":4,"7,4":5,"7,5":6,"7,6":6,"7,7":6,"7,8":6,"7,9":6,"7,10":6,"7,11":6,"7,12":6,"7,13":6,"7,14":6,"7,15":6,"7,16":6,"7,17":6,"7,18":6,"7,19":6,"7,20":6,"7,21":6,"7,22":6,"7,23":6,"7,24":6,"7,25":6,"7,26":6,"7,27":6,"7,28":6,"7,29":6,"7,30":6,"7,31":6,"7,32":6,"7,33":6,"7,34":6,"7,35":6,"7,36":6,"7,37":6,"7,38":6,"7,39":6,"7,40":6,"7,41":6,"7,42":6,"7,43":6,"7,44":6,"7,45":7,"8,4":5,"8,5":6,"8,6":6,"8,7":6,"8,8":6,"8,9":6,"8,10":6,"8,11":6,"8,12":6,"8,13":6,"8,14":6,"8,15":6,"8,16":6,"8,17":6,"8,18":6,"8,19":6,"8,20":6,"8,21":6,"8,22":6,"8,23":6,"8,24":6,"8,25":6,"8,26":6,"8,27":6,"8,28":6,"8,29":6,"8,30":6,"8,31":6,"8,32":6,"8,33":6,"8,34":6,"8,35":6,"8,36":6,"8,37":6,"8,38":6,"8,39":6,"8,40":7,"8,41":6,"8,42":6,"8,43":6,"8,44":6,"8,45":7,"9,4":5,"9,5":6,"9,6":6,"9,7":6,"9,8":6,"9,9":6,"9,10":6,"9,11":6,"9,12":6,"9,13":6,"9,14":6,"9,15":6,"9,16":6,"9,17":6,"9,18":6,"9,19":6,"9,20":6,"9,21":6,"9,22":6,"9,23":6,"9,24":6,"9,25":6,"9,26":6,"9,27":6,"9,28":6,"9,29":6,"9,30":6,"9,31":6,"9,32":6,"9,33":6,"9,34":6,"9,35":6,"9,36":6,"9,37":6,"9,38":6,"9,39":6,"9,40":7,"9,41":6,"9,42":6,"9,43":6,"9,44":6,"9,45":7,"10,4":5,"10,5":6,"10,6":6,"10,7":6,"10,8":6,"10,9":6,"10,10":6,"10,11":6,"10,12":6,"10,13":6,"10,14":6,"10,15":6,"10,16":6,"10,17":6,"10,18":6,"10,19":6,"10,20":6,"10,21":6,"10,22":6,"10,23":6,"10,24":6,"10,25":6,"10,26":6,"10,27":6,"10,28":6,"10,29":6,"10,30":6,"10,31":6,"10,32":6,"10,33":6,"10,34":6,"10,35":6,"10,36":6,"10,37":6,"10,38":6,"10,39":6,"10,40":7,"10,41":6,"10,42":6,"10,43":6,"10,44":6,"10,45":7,"11,4":8,"11,5":9,"11,6":9,"11,7":9,"11,8":9,"11,9":9,"11,10":9,"11,11":9,"11,12":9,"11,13":9,"11,14":9,"11,15":9,"11,16":9,"11,17":9,"11,18":9,"11,19":9,"11,20":9,"11,21":9,"11,22":9,"11,23":9,"11,24":9,"11,25":9,"11,26":9,"11,27":9,"11,28":9,"11,29":9,"11,30":9,"11,31":9,"11,32":9,"11,33":9,"11,34":9,"11,35":9,"11,36":9,"11,37":9,"11,38":9,"11,39":9,"11,40":9,"11,41":9,"11,42":9,"11,43":9,"11,44":9,"11,45":10,"12,4":8,"12,5":9,"12,6":9,"12,7":9,"12,8":9,"12,9":9,"12,10":9,"12,11":9,"12,12":9,"12,13":9,"12,14":9,"12,15":9,"12,16":9,"12,17":9,"12,18":9,"12,19":9,"12,20":9,"12,21":9,"12,22":9,"12,23":9,"12,24":9,"12,25":9,"12,26":9,"12,27":9,"12,28":9,"12,29":9,"12,30":9,"12,31":9,"12,32":9,"12,33":9,"12,34":9,"12,35":9,"12,36":9,"12,37":9,"12,38":9,"12,39":9,"12,40":9,"12,41":9,"12,42":9,"12,43":9,"12,44":9,"12,45":10,"13,4":8,"13,5":9,"13,6":9,"13,7":9,"13,8":9,"13,9":9,"13,10":9,"13,11":9,"13,12":9,"13,13":9,"13,14":9,"13,15":9,"13,16":9,"13,17":9,"13,18":9,"13,19":9,"13,20":9,"13,21":9,"13,22":9,"13,23":9,"13,24":9,"13,25":9,"13,26":9,"13,27":9,"13,28":9,"13,29":9,"13,30":9,"13,31":9,"13,32":9,"13,33":9,"13,34":9,"13,35":9,"13,36":9,"13,37":9,"13,38":9,"13,39":9,"13,40":9,"13,41":9,"13,42":9,"13,43":9,"13,44":9,"13,45":10,"14,4":5,"14,5":6,"14,6":6,"14,7":6,"14,8":6,"14,9":6,"14,10":6,"14,11":6,"14,12":6,"14,13":6,"14,14":6,"14,15":6,"14,16":6,"14,17":6,"14,18":6,"14,19":6,"14,20":6,"14,21":6,"14,22":6,"14,23":6,"14,24":6,"14,25":6,"14,26":6,"14,27":6,"14,28":6,"14,29":6,"14,30":6,"14,31":6,"14,32":6,"14,33":6,"14,34":6,"14,35":6,"14,36":6,"14,37":6,"14,38":6,"14,39":6,"14,40":7,"14,41":6,"14,42":6,"14,43":6,"14,44":6,"14,45":7,"15,4":5,"15,5":6,"15,6":6,"15,7":6,"15,8":6,"15,9":6,"15,10":6,"15,11":6,"15,12":6,"15,13":6,"15,14":6,"15,15":6,"15,16":6,"15,17":6,"15,18":6,"15,19":6,"15,20":6,"15,21":6,"15,22":6,"15,23":6,"15,24":6,"15,25":6,"15,26":6,"15,27":6,"15,28":6,"15,29":6,"15,30":6,"15,31":6,"15,32":6,"15,33":6,"15,34":6,"15,35":6,"15,36":6,"15,37":6,"15,38":6,"15,39":6,"15,40":7,"15,41":6,"15,42":6,"15,43":6,"15,44":6,"15,45":7,"16,4":5,"16,5":6,"16,6":6,"16,7":6,"16,8":6,"16,9":6,"16,10":6,"16,11":6,"16,12":6,"16,13":6,"16,14":6,"16,15":6,"16,16":6,"16,17":6,"16,18":6,"16,19":6,"16,20":6,"16,21":6,"16,22":6,"16,23":6,"16,24":6,"16,25":6,"16,26":6,"16,27":6,"16,28":6,"16,29":6,"16,30":6,"16,31":6,"16,32":6,"16,33":6,"16,34":6,"16,35":6,"16,36":6,"16,37":6,"16,38":6,"16,39":6,"16,40":7,"16,41":6,"16,42":6,"16,43":6,"16,44":6,"16,45":7,"17,4":5,"17,5":6,"17,6":6,"17,7":6,"17,8":6,"17,9":6,"17,10":6,"17,11":6,"17,12":6,"17,13":6,"17,14":6,"17,15":6,"17,16":6,"17,17":6,"17,18":6,"17,19":6,"17,20":6,"17,21":6,"17,22":6,"17,23":6,"17,24":6,"17,25":6,"17,26":6,"17,27":6,"17,28":6,"17,29":6,"17,30":6,"17,31":6,"17,32":6,"17,33":6,"17,34":6,"17,35":6,"17,36":6,"17,37":6,"17,38":6,"17,39":6,"17,40":7,"17,41":6,"17,42":6,"17,43":6,"17,44":6,"17,45":7,"18,4":5,"18,5":6,"18,6":6,"18,7":6,"18,8":6,"18,9":6,"18,10":6,"18,11":6,"18,12":6,"18,13":6,"18,14":6,"18,15":6,"18,16":6,"18,17":6,"18,18":6,"18,19":6,"18,20":6,"18,21":6,"18,22":6,"18,23":6,"18,24":6,"18,25":6,"18,26":6,"18,27":6,"18,28":6,"18,29":6,"18,30":6,"18,31":6,"18,32":6,"18,33":6,"18,34":6,"18,35":6,"18,36":6,"18,37":6,"18,38":6,"18,39":6,"18,40":7,"18,41":6,"18,42":6,"18,43":6,"18,44":6,"18,45":7,"19,4":11,"19,5":12,"19,6":12,"19,7":12,"19,8":12,"19,9":12,"19,10":12,"19,11":12,"19,12":12,"19,13":12,"19,14":12,"19,15":12,"19,16":12,"19,17":12,"19,18":12,"19,19":12,"19,20":12,"19,21":12,"19,22":12,"19,23":12,"19,24":12,"19,25":12,"19,26":12,"19,27":12,"19,28":12,"19,29":12,"19,30":12,"19,31":12,"19,32":12,"19,33":12,"19,34":12,"19,35":12,"19,36":12,"19,37":12,"19,38":12,"19,39":12,"19,40":13,"19,41":12,"19,42":12,"19,43":12,"19,44":12,"19,45":13,"20,2":0,"20,3":0,"20,4":0,"20,5":0,"20,6":0,"20,7":0,"20,8":0,"20,9":0,"20,10":0,"20,11":0,"20,12":0,"20,13":0,"20,14":0,"20,15":0,"20,16":0,"20,17":0,"20,18":0,"20,19":0,"20,20":0,"20,21":0,"20,22":0,"20,23":0,"20,24":0,"20,25":0,"20,26":0,"20,27":0,"20,28":0,"20,29":0,"20,30":0,"20,31":0,"20,32":0,"20,33":0,"20,34":0,"20,35":0,"20,36":0,"20,37":0,"20,38":0,"20,39":0,"20,40":0,"20,41":0,"20,42":0,"21,4":0,"21,12":0,"21,13":0,"21,14":0,"21,15":0,"21,16":0,"21,17":0,"21,18":0,"21,19":0,"21,20":0,"21,21":0,"21,22":0,"21,23":0,"21,24":0,"21,25":0,"21,26":0,"21,27":0,"21,28":0,"21,37":0,"21,38":0,"21,39":0,"21,40":0,"21,41":0,"21,42":0,"21,43":0,"21,44":0},"SheetStyle":{"FontFamily":0}},"Spans":["7,5,1,5","7,10,1,5","7,15,1,5","7,20,1,5","7,25,1,5","7,30,1,5","7,35,1,5","7,41,1,5","1,4,1,14","21,37,1,3","21,42,1,3","8,4,12,42","21,4,1,8","3,4,2,42","6,5,1,5","6,10,1,5","6,15,1,5","6,20,1,5","6,25,1,5","6,30,1,5","6,35,1,5","6,41,1,5"],"PageInfo":{"$type":"Forguncy.Model.Pages.NormalPage, ServerDesignerCommon","Title":"子件选择","AuthorizeInfo":{"VisitMode":4,"AllowVisitedRoles":["Admin","财务部","总经理","PMC","仓库","Administrator","副总经理（生产品质）","计划","生产主管","管理","涂布","行政"]},"RowBreakLines":[],"RepeatRangeSettings":[],"RelatedDataTableName":"Storage_jcsj_货品信息表"},"PrintInfo":{"Margin":{},"PaperSize":{}}}